src/pyluxcoreconsole.py
src/pyluxcoremaketx.py
src/pyluxcoremerge.py
pyluxcoretools/__init__.py
pyluxcoretools/pyluxcoreconsole/__init__.py
pyluxcoretools/pyluxcoreconsole/cmd.py
pyluxcoretools/pyluxcoremaketx/__init__.py
pyluxcoretools/pyluxcoremaketx/cmd.py
pyluxcoretools/pyluxcoremenu/__init__.py
pyluxcoretools/pyluxcoremenu/cmd.py
pyluxcoretools/pyluxcoremenu/menuwindow.py
pyluxcoretools/pyluxcoremenu/menuwindow.ui
pyluxcoretools/pyluxcoremerge/__init__.py
pyluxcoretools/pyluxcoremerge/cmd.py
pyluxcoretools/pyluxcorenetconsole/__init__.py
pyluxcoretools/pyluxcorenetconsole/addnodedialog.py
pyluxcoretools/pyluxcorenetconsole/addnodedialog.ui
pyluxcoretools/pyluxcorenetconsole/cmd.py
pyluxcoretools/pyluxcorenetconsole/mainwindow.py
pyluxcoretools/pyluxcorenetconsole/mainwindow.ui
pyluxcoretools/pyluxcorenetconsole/ui.py
pyluxcoretools/pyluxcorenetnode/__init__.py
pyluxcoretools/pyluxcorenetnode/cmd.py
pyluxcoretools/pyluxcorenetnode/mainwindow.py
pyluxcoretools/pyluxcorenetnode/mainwindow.ui
pyluxcoretools/pyluxcorenetnode/ui.py
pyluxcoretools/renderfarm/__init__.py
pyluxcoretools/renderfarm/renderfarm.py
pyluxcoretools/renderfarm/renderfarmfilmmerger.py
pyluxcoretools/renderfarm/renderfarmjobsingleimage.py
pyluxcoretools/renderfarm/renderfarmnode.py
pyluxcoretools/utils/__init__.py
pyluxcoretools/utils/args.py
pyluxcoretools/utils/filesystem.py
pyluxcoretools/utils/logevent.py
pyluxcoretools/utils/loghandler.py
pyluxcoretools/utils/md5.py
pyluxcoretools/utils/netbeacon.py
pyluxcoretools/utils/socket.py
pyluxcoretools/utils/uiloghandler.py
pyluxcoretools-2.9a1.post3.dist-info/METADATA
pyluxcoretools-2.9a1.post3.dist-info/WHEEL
pyluxcoretools-2.9a1.post3.dist-info/entry_points.txt
pyluxcoretools-2.9a1.post3.dist-info/licenses/LICENSE
pyluxcoretools-2.9a1.post3.dist-info/RECORD
