Metadata-Version: 2.3
Name: pyluxcoretools
Version: 2.9a1.post3
Summary: LuxCore Python Tools
Project-URL: Homepage, https://luxcorerender.org/
Project-URL: Documentation, http://wiki.luxcorerender.org/LuxCoreRender_Wiki
Project-URL: GitHub, https://github.com/LuxCoreRender/LuxCore
Author: Howetuft
Keywords: path tracing,pbr,physical based rendering,ray tracing,raytracing,rendering
Classifier: Development Status :: 7 - Inactive
Classifier: Intended Audience :: Developers
Classifier: License :: OSI Approved :: Apache Software License
Classifier: Programming Language :: Python :: 3.8
Classifier: Programming Language :: Python :: 3.9
Classifier: Programming Language :: Python :: 3.10
Classifier: Programming Language :: Python :: 3.11
Classifier: Programming Language :: Python :: 3.12
Classifier: Programming Language :: Python :: 3.13
Classifier: Topic :: Multimedia :: Graphics :: 3D Rendering
Requires-Python: >=3.8
Requires-Dist: pyluxcore
